ChangyongShujuwajueSuanfaZongjieJiPythonShixian/README.md
ChangyongShujuwajueSuanfaZongjieJiPythonShixian/__init__.py
ChangyongShujuwajueSuanfaZongjieJiPythonShixian/__main__.py
ChangyongShujuwajueSuanfaZongjieJiPythonShixian/file.pdf
ChangyongShujuwajueSuanfaZongjieJiPythonShixian/index.html
changyong_shujuwajue_suanfa_zongjie_ji_python_shixian-2024.3.2.0.dist-info/METADATA
changyong_shujuwajue_suanfa_zongjie_ji_python_shixian-2024.3.2.0.dist-info/WHEEL
changyong_shujuwajue_suanfa_zongjie_ji_python_shixian-2024.3.2.0.dist-info/entry_points.txt
changyong_shujuwajue_suanfa_zongjie_ji_python_shixian-2024.3.2.0.dist-info/top_level.txt
changyong_shujuwajue_suanfa_zongjie_ji_python_shixian-2024.3.2.0.dist-info/RECORD
